{
  "updated": "2026-04-23T02:09:54.283654",
  "region": "tokyo",
  "count": 98,
  "events": [
    {
      "title": "アウトドアデイジャパン東京2026",
      "date": "2026-04-04",
      "endDate": "2026-04-05",
      "place": "東京都",
      "url": "https://www.yoyogikoen.info/outdoor-day-japan-tokyo-2026/",
      "source": "yoyogi",
      "cost": "paid",
      "ages": [
        "toddler",
        "preschool",
        "elementary",
        "family"
      ],
      "cats": [
        "festival"
      ],
      "area": "other",
      "desc": "",
      "id": 1
    },
    {
      "title": "眞名子新 フリーライブ 公園公演",
      "date": "2026-04-07",
      "endDate": "2026-04-07",
      "place": "東京都",
      "url": "https://www.yoyogikoen.info/manakoarata-koenkouen-yoyogipark-2026/",
      "source": "yoyogi",
      "cost": "paid",
      "ages": [
        "toddler",
        "preschool",
        "elementary",
        "family"
      ],
      "cats": [
        "nature",
        "stage"
      ],
      "area": "other",
      "desc": "",
      "id": 2
    },
    {
      "title": "代々木公園わんわんカーニバル2026",
      "date": "2026-04-10",
      "endDate": "2026-04-12",
      "place": "東京都",
      "url": "https://www.yoyogikoen.info/yoyogi-park-wanwan-carnival-2026/",
      "source": "yoyogi",
      "cost": "paid",
      "ages": [
        "toddler",
        "preschool",
        "elementary",
        "family"
      ],
      "cats": [
        "nature"
      ],
      "area": "other",
      "desc": "",
      "id": 3
    },
    {
      "title": "アースガーデン 春 in アースデイ東京 2026",
      "date": "2026-04-18",
      "endDate": "2026-04-19",
      "place": "東京都",
      "url": "https://www.yoyogikoen.info/earthgarden-spring-earthday-tokyo-2026/",
      "source": "yoyogi",
      "cost": "paid",
      "ages": [
        "toddler",
        "preschool",
        "elementary",
        "family"
      ],
      "cats": [
        "festival"
      ],
      "area": "other",
      "desc": "",
      "id": 4
    },
    {
      "title": "アースデイ東京2026",
      "date": "2026-04-18",
      "endDate": "2026-04-19",
      "place": "東京都",
      "url": "https://www.yoyogikoen.info/earthday-tokyo-2026/",
      "source": "yoyogi",
      "cost": "paid",
      "ages": [
        "toddler",
        "preschool",
        "elementary",
        "family"
      ],
      "cats": [
        "festival"
      ],
      "area": "other",
      "desc": "",
      "id": 5
    },
    {
      "title": "TOKYO CRAFT BEER WEEK 2026",
      "date": "2026-04-20",
      "endDate": "2026-04-29",
      "place": "東京都",
      "url": "https://www.yoyogikoen.info/tokyo-craft-beer-week-2026/",
      "source": "yoyogi",
      "cost": "paid",
      "ages": [
        "toddler",
        "preschool",
        "elementary",
        "family"
      ],
      "cats": [
        "festival"
      ],
      "area": "other",
      "desc": "",
      "id": 6
    },
    {
      "title": "SHIBUYA CROSS-CULTURE FEST",
      "date": "2026-04-25",
      "endDate": "2026-04-26",
      "place": "東京都",
      "url": "https://www.yoyogikoen.info/shibuya-cross-culture-fest-2026/",
      "source": "yoyogi",
      "cost": "paid",
      "ages": [
        "toddler",
        "preschool",
        "elementary",
        "family"
      ],
      "cats": [
        "festival"
      ],
      "area": "other",
      "desc": "",
      "id": 7
    },
    {
      "title": "第97回メーデー中央大会",
      "date": "2026-04-29",
      "endDate": "2026-04-29",
      "place": "東京都",
      "url": "https://www.yoyogikoen.info/mayday-central-tournament-2026/",
      "source": "yoyogi",
      "cost": "paid",
      "ages": [
        "toddler",
        "preschool",
        "elementary",
        "family"
      ],
      "cats": [
        "festival"
      ],
      "area": "other",
      "desc": "",
      "id": 8
    },
    {
      "title": "第97回中央メーデー",
      "date": "2026-05-01",
      "endDate": "2026-05-01",
      "place": "東京都",
      "url": "https://www.yoyogikoen.info/mayday-2026-central-tokyo/",
      "source": "yoyogi",
      "cost": "paid",
      "ages": [
        "toddler",
        "preschool",
        "elementary",
        "family"
      ],
      "cats": [
        "festival"
      ],
      "area": "other",
      "desc": "",
      "id": 9
    },
    {
      "title": "SHIBUYA ONE PARK 2026 - PARK ATTACK & 台湾發祭 -",
      "date": "2026-05-02",
      "endDate": "2026-05-05",
      "place": "東京都",
      "url": "https://www.yoyogikoen.info/shibuya-one-park-2026/",
      "source": "yoyogi",
      "cost": "paid",
      "ages": [
        "toddler",
        "preschool",
        "elementary",
        "family"
      ],
      "cats": [
        "festival"
      ],
      "area": "other",
      "desc": "",
      "id": 10
    },
    {
      "title": "タイフェスティバル東京2026",
      "date": "2026-05-09",
      "endDate": "2026-05-10",
      "place": "東京都",
      "url": "https://www.yoyogikoen.info/thai-festival-2026/",
      "source": "yoyogi",
      "cost": "paid",
      "ages": [
        "toddler",
        "preschool",
        "elementary",
        "family"
      ],
      "cats": [
        "festival"
      ],
      "area": "other",
      "desc": "",
      "id": 11
    },
    {
      "title": "OKINAWA FES Milafete",
      "date": "2026-05-16",
      "endDate": "2026-05-17",
      "place": "東京都",
      "url": "https://www.yoyogikoen.info/okinawa-fes-milafete-2026/",
      "source": "yoyogi",
      "cost": "paid",
      "ages": [
        "toddler",
        "preschool",
        "elementary",
        "family"
      ],
      "cats": [
        "festival"
      ],
      "area": "other",
      "desc": "",
      "id": 12
    },
    {
      "title": "東京ナイトマーケット",
      "date": "2026-05-20",
      "endDate": "2026-05-24",
      "place": "東京都",
      "url": "https://www.yoyogikoen.info/tokyo-night-market-2026-may/",
      "source": "yoyogi",
      "cost": "paid",
      "ages": [
        "toddler",
        "preschool",
        "elementary",
        "family"
      ],
      "cats": [
        "festival"
      ],
      "area": "other",
      "desc": "",
      "id": 13
    },
    {
      "title": "ラオスフェスティバル2026",
      "date": "2026-05-23",
      "endDate": "2026-05-24",
      "place": "東京都",
      "url": "https://www.yoyogikoen.info/laos-festival-2026/",
      "source": "yoyogi",
      "cost": "paid",
      "ages": [
        "toddler",
        "preschool",
        "elementary",
        "family"
      ],
      "cats": [
        "festival"
      ],
      "area": "other",
      "desc": "",
      "id": 14
    },
    {
      "title": "ベトナムフェスティバル2026",
      "date": "2026-05-30",
      "endDate": "2026-05-31",
      "place": "東京都",
      "url": "https://www.yoyogikoen.info/vietnam-festival-2026-yoyogi/",
      "source": "yoyogi",
      "cost": "paid",
      "ages": [
        "toddler",
        "preschool",
        "elementary",
        "family"
      ],
      "cats": [
        "festival"
      ],
      "area": "other",
      "desc": "",
      "id": 15
    },
    {
      "title": "Tokyo Pride 2026",
      "date": "2026-06-06",
      "endDate": "2026-06-07",
      "place": "東京都",
      "url": "https://www.yoyogikoen.info/tokyo-pride-2026/",
      "source": "yoyogi",
      "cost": "paid",
      "ages": [
        "toddler",
        "preschool",
        "elementary",
        "family"
      ],
      "cats": [
        "festival"
      ],
      "area": "other",
      "desc": "",
      "id": 16
    },
    {
      "title": "アフリカヘリテイジフェスティバル in 代々木公園 2026",
      "date": "2026-06-20",
      "endDate": "2026-06-21",
      "place": "東京都",
      "url": "https://www.yoyogikoen.info/africa-heritage-festival-yoyogi-park-2026/",
      "source": "yoyogi",
      "cost": "paid",
      "ages": [
        "toddler",
        "preschool",
        "elementary",
        "family"
      ],
      "cats": [
        "nature",
        "festival"
      ],
      "area": "other",
      "desc": "",
      "id": 17
    },
    {
      "title": "ジャマイカフェスティバル 2026 レゲエ＆キュイジーヌ in 東京",
      "date": "2026-06-20",
      "endDate": "2026-06-21",
      "place": "東京都",
      "url": "https://www.yoyogikoen.info/jamaica-festival-2026-tokyo/",
      "source": "yoyogi",
      "cost": "paid",
      "ages": [
        "toddler",
        "preschool",
        "elementary",
        "family"
      ],
      "cats": [
        "festival"
      ],
      "area": "other",
      "desc": "",
      "id": 18
    },
    {
      "title": "星と太陽のマーケット produced by 東京ナイトマーケット",
      "date": "2026-07-01",
      "endDate": "2026-07-05",
      "place": "東京都",
      "url": "https://www.yoyogikoen.info/hoshi-to-taiyou-no-market-2026/",
      "source": "yoyogi",
      "cost": "paid",
      "ages": [
        "toddler",
        "preschool",
        "elementary",
        "family"
      ],
      "cats": [
        "festival"
      ],
      "area": "other",
      "desc": "",
      "id": 19
    },
    {
      "title": "アースガーデン 夏 ヨルイチ 2026",
      "date": "2026-07-03",
      "endDate": "2026-07-05",
      "place": "東京都",
      "url": "https://www.yoyogikoen.info/earthgarden-summer-yoruichi-2026/",
      "source": "yoyogi",
      "cost": "paid",
      "ages": [
        "toddler",
        "preschool",
        "elementary",
        "family"
      ],
      "cats": [
        "festival"
      ],
      "area": "other",
      "desc": "",
      "id": 20
    },
    {
      "title": "原宿表参道元氣祭スーパーよさこい 2026",
      "date": "2026-08-29",
      "endDate": "2026-08-30",
      "place": "東京都",
      "url": "https://www.yoyogikoen.info/harajuku-omotesando-genki-super-yosakoi-2026/",
      "source": "yoyogi",
      "cost": "paid",
      "ages": [
        "toddler",
        "preschool",
        "elementary",
        "family"
      ],
      "cats": [
        "festival"
      ],
      "area": "other",
      "desc": "",
      "id": 21
    },
    {
      "title": "ナマステ・インディア2026",
      "date": "2026-09-26",
      "endDate": "2026-09-27",
      "place": "東京都",
      "url": "https://www.yoyogikoen.info/namaste-india-2026/",
      "source": "yoyogi",
      "cost": "paid",
      "ages": [
        "toddler",
        "preschool",
        "elementary",
        "family"
      ],
      "cats": [
        "festival"
      ],
      "area": "other",
      "desc": "",
      "id": 22
    },
    {
      "title": "カリブ・ラテンアメリカストリート代々木2026",
      "date": "2026-10-17",
      "endDate": "2026-10-18",
      "place": "東京都",
      "url": "https://www.yoyogikoen.info/caribbean-latin-america-street-yoyogi-2026/",
      "source": "yoyogi",
      "cost": "paid",
      "ages": [
        "toddler",
        "preschool",
        "elementary",
        "family"
      ],
      "cats": [
        "festival"
      ],
      "area": "other",
      "desc": "",
      "id": 23
    },
    {
      "title": "アースガーデン 秋 2026",
      "date": "2026-10-24",
      "endDate": "2026-10-25",
      "place": "東京都",
      "url": "https://www.yoyogikoen.info/earthgarden-autumn-2026/",
      "source": "yoyogi",
      "cost": "paid",
      "ages": [
        "toddler",
        "preschool",
        "elementary",
        "family"
      ],
      "cats": [
        "festival"
      ],
      "area": "other",
      "desc": "",
      "id": 24
    },
    {
      "title": "東京雪祭2026",
      "date": "2026-10-31",
      "endDate": "2026-11-01",
      "place": "東京都",
      "url": "https://www.yoyogikoen.info/tokyo-snow-festival-2026/",
      "source": "yoyogi",
      "cost": "paid",
      "ages": [
        "toddler",
        "preschool",
        "elementary",
        "family"
      ],
      "cats": [
        "festival"
      ],
      "area": "other",
      "desc": "",
      "id": 25
    },
    {
      "title": "フィエスタ・デ・エスパーニャ 2026",
      "date": "2026-11-14",
      "endDate": "2026-11-15",
      "place": "東京都",
      "url": "https://www.yoyogikoen.info/fiesta-de-espana-2026/",
      "source": "yoyogi",
      "cost": "paid",
      "ages": [
        "toddler",
        "preschool",
        "elementary",
        "family"
      ],
      "cats": [
        "festival"
      ],
      "area": "other",
      "desc": "",
      "id": 26
    },
    {
      "title": "「ふんわりローズバッグ」手作りワークショップ",
      "date": "2026-04-23",
      "endDate": "2026-04-23",
      "place": "東京都",
      "url": "https://iko-yo.net/events?prefecture_ids[]=13",
      "source": "ikoy",
      "cost": "paid",
      "ages": [
        "family"
      ],
      "cats": [
        "workshop"
      ],
      "area": "other",
      "desc": "布バッグは色々作った事があっても、このような丸い形の物はやった事がない、という方も多いのではないでしょうか。\n\n丸いバッグは、ただ布を丸くしただけではこのような形にはなりません。\nふっくらふんわりとしたフォルムをキープさせるには、製図はもち",
      "id": 27
    },
    {
      "title": "5月【新宿　平日午前または夜】練り切りレッスンと茶道体験",
      "date": "2026-04-23",
      "endDate": "2026-04-23",
      "place": "東京都",
      "url": "https://iko-yo.net/events?prefecture_ids[]=13",
      "source": "ikoy",
      "cost": "paid",
      "ages": [
        "family"
      ],
      "cats": [
        "workshop"
      ],
      "area": "other",
      "desc": "練り切りは、和菓子屋さんやデパートで買うモノ！？\nいえいえ、\nご自分でも、ご家庭のキッチンでも作れるお菓子なのです！\n\n職人さんが作るような素敵な和菓子の練り切り、\nご自分でも作ってみませんか♡\n\n毎月、レッスンで作る練り切りのテーマが変わ",
      "id": 28
    },
    {
      "title": "【浅草】超初心者向け 鉛筆デッサン基礎講座［都度利用絵...",
      "date": "2026-04-23",
      "endDate": "2026-04-23",
      "place": "東京都",
      "url": "https://iko-yo.net/events?prefecture_ids[]=13",
      "source": "ikoy",
      "cost": "paid",
      "ages": [
        "family"
      ],
      "cats": [
        "festival"
      ],
      "area": "other",
      "desc": "レッスン内容\n・単発都度受講制\n・モチーフ：りんご（初回体験）\n・少人数制（まわりが気にならない環境です）\n\n絵を描くことのよさは上達することや、自分の作品が生まれることはもちろんのこと、集中して物を見ることでリラックス効果があります。普段",
      "id": 29
    },
    {
      "title": "【洗足学園】2026年度入試 体験レッスン＆最新考査解...",
      "date": "2026-04-23",
      "endDate": "2026-04-23",
      "place": "東京都",
      "url": "https://iko-yo.net/events?prefecture_ids[]=13",
      "source": "ikoy",
      "cost": "paid",
      "ages": [
        "elementary"
      ],
      "cats": [
        "workshop"
      ],
      "area": "other",
      "desc": "こんにちは、AKANON事務局です。\n\n【洗足学園小学校】2026年度入試対策 体験レッスン＆最新考査解説セミナー\nのご案内です♪\n\n\n実際の考査を意識したレッスンと、最新傾向を整理する保護者向けセミナーを組み合わせ、\nより実践的にご理解い",
      "id": 30
    },
    {
      "title": "国営昭和記念公園 こもれびの里「農家でうどん作り体験」",
      "date": "2026-04-23",
      "endDate": "2026-04-23",
      "place": "東京都",
      "url": "https://iko-yo.net/events?prefecture_ids[]=13",
      "source": "ikoy",
      "cost": "paid",
      "ages": [
        "family"
      ],
      "cats": [
        "workshop",
        "nature"
      ],
      "area": "other",
      "desc": "里で収穫した小麦粉を使ってうどん作りから食べるまでを体験できる。参加者には里で収穫した小麦粉をお土産として提供。申込フォームによる事前申込制で定員は16名。締め切り（5/12）後に抽選し、当選者のみ連絡する。1テーブル4名での体験となるため",
      "id": 31
    },
    {
      "title": "センター開放日「保護犬に会いに行こう！」(世田谷譲渡セ...",
      "date": "2026-04-23",
      "endDate": "2026-04-23",
      "place": "東京都",
      "url": "https://iko-yo.net/events?prefecture_ids[]=13",
      "source": "ikoy",
      "cost": "paid",
      "ages": [
        "family"
      ],
      "cats": [
        "festival"
      ],
      "area": "other",
      "desc": "開放日とは、予約不要で好きな時間（11時〜17時迄）に行ける日のこと。少しでも保護犬に興味のある人、将来的に保護犬を迎えたいと思っている人、保護犬と会ってみたい人など、どんな人でも参加可能。ワンコたちが待っている！",
      "id": 32
    },
    {
      "title": "ネコヨガ（5月）",
      "date": "2026-04-23",
      "endDate": "2026-04-23",
      "place": "東京都",
      "url": "https://iko-yo.net/events?prefecture_ids[]=13",
      "source": "ikoy",
      "cost": "paid",
      "ages": [
        "family"
      ],
      "cats": [
        "festival"
      ],
      "area": "other",
      "desc": "ネコヨガは、保護猫たちに囲まれた自由な空間でおこなう、やさしいヨガ。参加費の一部は、保護猫たちへの寄付となる。ヨガで身体はぽかぽか、猫助けできて心もぽかぽかヨガが初めての人も、身体が硬くても大丈夫。猫好きさんならだれでも参加OK。",
      "id": 33
    },
    {
      "title": "第18回 隅田川水面の祭典 2026",
      "date": "2026-04-23",
      "endDate": "2026-04-23",
      "place": "東京都",
      "url": "https://iko-yo.net/events?prefecture_ids[]=13",
      "source": "ikoy",
      "cost": "paid",
      "ages": [
        "family"
      ],
      "cats": [
        "festival"
      ],
      "area": "other",
      "desc": "公益財団法人マリンスポーツ財団の協力により、水上バイクフリースタイルデモンストレーション、アクアボードフライングショーを開催。夏先取りマリンイベントでは「プールでマリンスポーツ体験」、「ライフジャケットクイズラリー」、「SDGｓワークショッ",
      "id": 34
    },
    {
      "title": "BEER HOUR FEST in 東京タワー 2026",
      "date": "2026-04-23",
      "endDate": "2026-04-23",
      "place": "東京都",
      "url": "https://iko-yo.net/events?prefecture_ids[]=13",
      "source": "ikoy",
      "cost": "paid",
      "ages": [
        "family"
      ],
      "cats": [
        "festival"
      ],
      "area": "other",
      "desc": "「BEER HOUR FEST」が、今年のGWも東京タワーに帰ってくる。東京タワーを見上げる絶好のロケーションのもと、ドイツビールやグルメを気軽に楽しめるビールフェス。ドイツで開催される世界最大規模のビール祭、オクトーバーフェストの雰囲気を",
      "id": 35
    },
    {
      "title": "まろにえぴよぴよコンサート",
      "date": "2026-04-23",
      "endDate": "2026-04-23",
      "place": "東京都",
      "url": "https://iko-yo.net/events?prefecture_ids[]=13",
      "source": "ikoy",
      "cost": "paid",
      "ages": [
        "family"
      ],
      "cats": [
        "concert"
      ],
      "area": "other",
      "desc": "毎回好評の、ベビーカーのまま入れて、親子でいっしょに楽しめるコンサート。先着200名。入場前に手作り楽器を作ったら一緒に演奏できるよ（指定曲のみ。参加可能な曲以外では手作り楽器の使用は不可）。また、参加者全員にるるめちゃんシールをプレゼント",
      "id": 36
    },
    {
      "title": "第70回江戸川区特産バラ品評展示即売会",
      "date": "2026-04-23",
      "endDate": "2026-04-23",
      "place": "東京都",
      "url": "https://iko-yo.net/events?prefecture_ids[]=13",
      "source": "ikoy",
      "cost": "paid",
      "ages": [
        "family"
      ],
      "cats": [
        "museum"
      ],
      "area": "other",
      "desc": "【概要文】江戸川区花卉園芸組合の方々が丹精込めて育てたバラや花苗などの展示販売「第70回江戸川区特産バラ品評展示即売会」を開催します。本イベントは第70回を節目とし、今回の開催をもちまして終了する運びとなりました。最後の機会に、ぜひご来場く",
      "id": 37
    },
    {
      "title": "昔の手仕事体験～糸車で糸を紡ごう～",
      "date": "2026-04-23",
      "endDate": "2026-04-23",
      "place": "東京都",
      "url": "https://iko-yo.net/events?prefecture_ids[]=13",
      "source": "ikoy",
      "cost": "paid",
      "ages": [
        "family"
      ],
      "cats": [
        "workshop"
      ],
      "area": "other",
      "desc": "【概要文】かつて江戸川区内の農家では綿を栽培していました。\n江戸時代そのままの佇まいを残す一之江名主屋敷で、\n綿から糸を紡ぎ、昔の手仕事体験をしましょう。",
      "id": 38
    },
    {
      "title": "４組限定！仙川【親子ラウンジtoiro】ベビーマッサー...",
      "date": "2026-04-28",
      "endDate": "2026-04-28",
      "place": "東京都",
      "url": "https://iko-yo.net/events?prefecture_ids[]=13",
      "source": "ikoy",
      "cost": "paid",
      "ages": [
        "family"
      ],
      "cats": [
        "festival"
      ],
      "area": "other",
      "desc": "仙川駅より徒歩5分！\n【親子ラウンジ toiro】さんにてベビーマッサージ体験会を行います♬\n★ランチとレッスン中のお写真プレゼント！\ntoiroさんは、ご予約でフリードリンク・お菓子がついてきます！！\n2026年4月28日に新たにオープン",
      "id": 39
    },
    {
      "title": "6/6(土)ドレミブラザーズ！楽器の日スペシャルコンサ...",
      "date": "2026-04-23",
      "endDate": "2026-04-23",
      "place": "東京都",
      "url": "https://iko-yo.net/events?prefecture_ids[]=13",
      "source": "ikoy",
      "cost": "paid",
      "ages": [
        "family"
      ],
      "cats": [
        "festival"
      ],
      "area": "other",
      "desc": "≪ドレミブラザーズ！楽器の日スペシャルコンサート～親子で楽しむ、音とリズムの参加型ステージ！～」/参加型コンサート/音楽イベント≫\n\n管楽器アンサンブル「ドレミブラザーズ」が子供たちを楽しい音楽の世界に連れていくよ！\n\nワクワク！ドキドキ★",
      "id": 40
    },
    {
      "title": "2026 せいしん こどもCafé 5.6月ラインナップ",
      "date": "2026-04-23",
      "endDate": "2026-04-23",
      "place": "東京都",
      "url": "https://iko-yo.net/events?prefecture_ids[]=13",
      "source": "ikoy",
      "cost": "paid",
      "ages": [
        "family"
      ],
      "cats": [
        "festival"
      ],
      "area": "other",
      "desc": "5月と6月の『せいしん こどもカフェ』の活動日と内容の案内です。\n5月は13日にちょうちょづくり、25日に親子でキッズヨガを開催します。\n6月は3日にトイレットペーパー遊びとてるてるぼうず作り、10日に絵の具遊び（手形スタンプ）、17日にミ",
      "id": 41
    },
    {
      "title": "講談社『全国訪問おはなし隊』5/30「青山公園キッズフ...",
      "date": "2026-04-23",
      "endDate": "2026-04-23",
      "place": "東京都",
      "url": "https://iko-yo.net/events?prefecture_ids[]=13",
      "source": "ikoy",
      "cost": "paid",
      "ages": [
        "family"
      ],
      "cats": [
        "nature"
      ],
      "area": "other",
      "desc": "講談社の『全国訪問おはなし隊』が5/30「青山公園キッズフェスタ」に参加します！\nキャラバンカーに載せた、約550冊の絵本を自由に読んでいただく自由閲覧と、おはなし隊隊長による おはなし会（絵本の読み聞かせと紙芝居） を開催予定です。\n※雨",
      "id": 42
    },
    {
      "title": "写真展「ひととき2026GW 〜Old and New〜」",
      "date": "2026-04-23",
      "endDate": "2026-04-23",
      "place": "東京都",
      "url": "https://iko-yo.net/events?prefecture_ids[]=13",
      "source": "ikoy",
      "cost": "paid",
      "ages": [
        "family"
      ],
      "cats": [
        "festival"
      ],
      "area": "other",
      "desc": "ちょっと普通の写真展とは違う「ひととき」\n今回はGWに開催！\n\nご家族で、友人と、一人でも\n来たら遊べるお祭り写真展！\nお子様プレゼントや抽選会も開催！\n\nとっても貴重な体験ができる「現像体験」等のワークショップもありますので\n是非遊びに.",
      "id": 43
    },
    {
      "title": "国際博物館の日記念イベント「みんなで博物館を楽しもう！」",
      "date": "2026-05-18",
      "endDate": "2026-05-24",
      "place": "東京都",
      "url": "https://iko-yo.net/events?prefecture_ids[]=13",
      "source": "ikoy",
      "cost": "paid",
      "ages": [
        "family"
      ],
      "cats": [
        "museum"
      ],
      "area": "other",
      "desc": "毎年5月18日、世界の博物館では「国際博物館の日」を記念し、前後の期間に博物館の社会的役割を広く知ってもらうためのイベントを行います。\n東京農工大学科学博物館では、5月24日(日)に記念イベントを開催します。\n\n〇企画展「シルクが切り開く未",
      "id": 44
    },
    {
      "title": "鶴川駅前図書館 おはなし会",
      "date": "2026-04-23",
      "endDate": "2026-04-23",
      "place": "東京都",
      "url": "https://iko-yo.net/events?prefecture_ids[]=13",
      "source": "ikoy",
      "cost": "paid",
      "ages": [
        "toddler",
        "preschool",
        "elementary"
      ],
      "cats": [
        "festival"
      ],
      "area": "other",
      "desc": "鶴川駅前図書館で開催されるおはなし会です。\n幼児・小学生向け、英語のおはなし会、0・1・2歳向けあっぷっぷおはなし会があります。\n当日先着10組までの参加で、事前予約は不要です。\n英語のおはなし会は5月から第2木曜日開催に変更になりました。",
      "id": 45
    },
    {
      "title": "５月４日～６日　イーアス高尾　ドームプラネットアドベン...",
      "date": "2026-04-23",
      "endDate": "2026-04-23",
      "place": "東京都",
      "url": "https://iko-yo.net/events?prefecture_ids[]=13",
      "source": "ikoy",
      "cost": "paid",
      "ages": [
        "family"
      ],
      "cats": [
        "festival"
      ],
      "area": "other",
      "desc": "イーアス高尾にて、寝て観る３６０度地球体験型アトラクション『ドームプラネット』と、ワークショップ『アンモナイトのレプリカ作り』を同時開催します。\n\nドームプラネットでは、３６０度に広がる映像で、巨大沈没船の世界を探検！\nまるで海の中に入り込",
      "id": 46
    },
    {
      "title": "紫陽花とローズのバレッタ@東京ドームシティ",
      "date": "2026-04-23",
      "endDate": "2026-04-23",
      "place": "東京都",
      "url": "https://iko-yo.net/events?prefecture_ids[]=13",
      "source": "ikoy",
      "cost": "paid",
      "ages": [
        "family"
      ],
      "cats": [
        "nature"
      ],
      "area": "other",
      "desc": "季節の花「紫陽花とローズ」の高品質なアーティフィシャルフラワーを使用したヘアアクセサリーを作ります。\n紫陽花（アジサイ）の中心にパールをあしらった上品で華やかなデザインのバレッタが完成します。\nハーフアップやまとめ髪に留めるだけで、後ろ姿が",
      "id": 47
    },
    {
      "title": "母の日スペシャル アイシングクッキー体験@東京ドームシティ",
      "date": "2026-04-23",
      "endDate": "2026-04-23",
      "place": "東京都",
      "url": "https://iko-yo.net/events?prefecture_ids[]=13",
      "source": "ikoy",
      "cost": "paid",
      "ages": [
        "family"
      ],
      "cats": [
        "workshop"
      ],
      "area": "other",
      "desc": "世界にひとつのオリジナルアイシングクッキーを作りましょう！\n初めての方やお子様でも楽しく参加できるクッキーデコレーションワークショップです。\n母の日のプレゼントにもぴったりのギフトボックスに入れてお持ち帰りいただけます。\n国産オーガニック小",
      "id": 48
    },
    {
      "title": "足立吹奏楽団 第34回スプリングコンサート",
      "date": "2026-04-23",
      "endDate": "2026-04-23",
      "place": "東京都",
      "url": "https://iko-yo.net/events?prefecture_ids[]=13",
      "source": "ikoy",
      "cost": "paid",
      "ages": [
        "family"
      ],
      "cats": [
        "concert"
      ],
      "area": "other",
      "desc": "足立吹奏楽団による第34回スプリングコンサートを開催します。\n\n指　揮：浅利 真（常任指揮者）、酒井 達哉\n司　会：堀江 慶子\n吹奏楽：足立吹奏楽団\n\n※チケット販売中\nチケットプレイガイド\n●ギャラクシティ●\n①窓口販売　9：00～2..",
      "id": 49
    },
    {
      "title": "子どもといっしょにクラシック　0～3歳『ロビーでよちよ...",
      "date": "2026-04-23",
      "endDate": "2026-04-23",
      "place": "東京都",
      "url": "https://iko-yo.net/events?prefecture_ids[]=13",
      "source": "ikoy",
      "cost": "paid",
      "ages": [
        "toddler",
        "family"
      ],
      "cats": [
        "concert"
      ],
      "area": "other",
      "desc": "0～3歳児とその保護者向けに、響き豊かな第一生命ホール ロビーでコンサートを開催します。\n今回はヴァイオリン、チェロ、フルート、ホルン、打楽器が登場します。\n親子いっしょに、すぐ目の前で奏でられる迫力の生演奏をお楽しみください。\n\n【出演】",
      "id": 50
    },
    {
      "title": "恵畑ゆうさんと”番組収録体験”にチャレンジ！！",
      "date": "2026-04-23",
      "endDate": "2026-04-23",
      "place": "東京都",
      "url": "https://iko-yo.net/events?prefecture_ids[]=13",
      "source": "ikoy",
      "cost": "paid",
      "ages": [
        "family"
      ],
      "cats": [
        "workshop"
      ],
      "area": "other",
      "desc": "Eテレ「ワンワンわんだーらんど」のゆうくんこと恵畑ゆうさんと、レッスンでダンスを覚えて番組収録にチャレンジしよう！\n本番さながらの体験の中で「挑戦する力」を育てる、子ども番組づくりから考えられた教育プログラムです。\n番組収録が心配なお子様は",
      "id": 51
    },
    {
      "title": "すいようのあそびくらぶ【平日半日の3歳～小２までのソト...",
      "date": "2026-04-23",
      "endDate": "2026-04-23",
      "place": "東京都",
      "url": "https://iko-yo.net/events?prefecture_ids[]=13",
      "source": "ikoy",
      "cost": "paid",
      "ages": [
        "toddler"
      ],
      "cats": [
        "festival"
      ],
      "area": "other",
      "desc": "《すいようのあそびくらぶ》は、保護者の方と離れ、スタッフと子どもたちだけで、水曜日の午後2時間半、多摩川河川敷で活動します。\n\n川辺を探検したり、広場で思いっきり走り回ったり、虫取り網を持って生き物を探したり…\n子どもたちの「やりたい」を大",
      "id": 52
    },
    {
      "title": "＜初心者＞ドレッシングABC❌クラブハウスサンド❌豆乳...",
      "date": "2026-04-23",
      "endDate": "2026-04-23",
      "place": "東京都",
      "url": "https://iko-yo.net/events?prefecture_ids[]=13",
      "source": "ikoy",
      "cost": "paid",
      "ages": [
        "family"
      ],
      "cats": [
        "festival"
      ],
      "area": "other",
      "desc": "料理初心者、大歓迎！\n講師を中心に、みなさんで、楽しく作っていく参加型実習。\n男性も気軽にご参加いただけます。\n\n◉良い素材で作るドレッシング→各自実習\n　サウザンアイランド、濃厚胡麻ドレッシング\n◉クラブハウスサンドイッチ→各自実習\n◉豆",
      "id": 53
    },
    {
      "title": "【こどもの日特別企画】4/25（土）水引で作る世界にひ...",
      "date": "2026-04-23",
      "endDate": "2026-04-23",
      "place": "東京都",
      "url": "https://iko-yo.net/events?prefecture_ids[]=13",
      "source": "ikoy",
      "cost": "paid",
      "ages": [
        "family"
      ],
      "cats": [
        "festival"
      ],
      "area": "other",
      "desc": "新企画！水引作家さんによる特別講座を開催します😊\n\n水引ってご存知ですか？贈答品や祝儀袋の表紙にかけられる飾り紐のことです。\n誰もが一度は目にしたことがあるのではないでしょうか。\n\n伝統的な贈答の飾り（祝儀袋）としてだけでなく、ハンドメイド",
      "id": 54
    },
    {
      "title": "「もっと自由に歌いたい」を叶える！藝大卒×ハリウッド式...",
      "date": "2026-04-23",
      "endDate": "2026-04-23",
      "place": "東京都",
      "url": "https://iko-yo.net/events?prefecture_ids[]=13",
      "source": "ikoy",
      "cost": "paid",
      "ages": [
        "family"
      ],
      "cats": [
        "festival"
      ],
      "area": "other",
      "desc": "​＜こんなお悩みありませんか？＞\n​・「高い声が出ない」「声がこもる」など、自分の歌い方にコンプレックスがある\n・歌うのは好きだけど、ボイトレは敷居が高い…厳しいレッスンは苦手\n・日々の仕事や忙しさで、つい「自分の本当の気持ち」を押し込めて",
      "id": 55
    },
    {
      "title": "【4月限定】スズランの香るアレンジメント",
      "date": "2026-04-23",
      "endDate": "2026-04-23",
      "place": "東京都",
      "url": "https://iko-yo.net/events?prefecture_ids[]=13",
      "source": "ikoy",
      "cost": "paid",
      "ages": [
        "family"
      ],
      "cats": [
        "festival"
      ],
      "area": "other",
      "desc": "手まり草の丘の上に、スズランが咲いてるような\nそんなイメージで、作ってみましょう。\n\nラウンドアレンジメントと、パラレルアレンジの\n基本を組み合わせたアレンジメントになります。\n\nどんなアレンジメントも、基本の形をもとにデザインを決めること",
      "id": 56
    },
    {
      "title": "文字サイズ",
      "date": "2026-04-23",
      "endDate": "2026-04-23",
      "place": "東京都",
      "url": "https://kodomo-smile.metro.tokyo.lg.jp/events",
      "source": "tokyo",
      "cost": "paid",
      "ages": [
        "family"
      ],
      "cats": [
        "festival"
      ],
      "area": "other",
      "desc": "",
      "id": 57
    },
    {
      "title": "【取材レポート】子どもと「命」を語り合う65分。又吉直樹さんと没入する『マンガローグ：火の鳥』。手塚治虫が未来の君たちへ託したメッセージとは？",
      "date": "2026-04-21",
      "endDate": "2026-04-21",
      "place": "東京都",
      "url": "https://www.kids-event.jp/report/20260421_mangalogue_hinotori/",
      "source": "kids",
      "cost": "paid",
      "ages": [
        "family"
      ],
      "cats": [
        "nature"
      ],
      "area": "other",
      "desc": "『マンガローグ：火の鳥』のゲネプロ（最終リハーサル）が2026年4月21日（火）に開催！又吉直樹さんがマンガローガーを務め新しい『火の鳥』を見せてくれました。さらにキャストの夏木マリさん、古田新太さん、花總まりさん、千葉一磨さん、新内眞衣さ",
      "id": 58
    },
    {
      "title": "『ザ・スーパーマリオギャラクシー・ムービー』特製ノート プレゼント！",
      "date": "2026-04-24",
      "endDate": "2026-04-24",
      "place": "東京都",
      "url": "https://www.kids-event.jp/present/20260424_mario_present/",
      "source": "kids",
      "cost": "paid",
      "ages": [
        "family"
      ],
      "cats": [
        "festival"
      ],
      "area": "other",
      "desc": "待望の続編『ザ・スーパーマリオギャラクシー・ムービー』が2026年4月24日（金）より全国公開！ 映画の公開を記念して『ザ・スーパーマリオギャラクシー・ムービー』特製ノートをプレゼント！",
      "id": 59
    },
    {
      "title": "映画『トムとジェリー時をこえる魔法の羅針盤』オリジナル巾着プレゼント！",
      "date": "2026-05-29",
      "endDate": "2026-05-29",
      "place": "東京都",
      "url": "https://www.kids-event.jp/present/20260529_tomandjerry_present/",
      "source": "kids",
      "cost": "paid",
      "ages": [
        "family"
      ],
      "cats": [
        "festival"
      ],
      "area": "other",
      "desc": "世代を超えて世界中で愛される “トムとジェリー” 最新映画『トムとジェリー時をこえる魔法の羅針盤』が2026年5月29日（金）全国公開！それを記念して映画『トムとジェリー』のオリジナル巾着をプレゼント！",
      "id": 60
    },
    {
      "title": "MANGALOGUE（マンガローグ）：火の鳥",
      "date": "2026-03-28",
      "endDate": "2026-04-22",
      "place": "東京都",
      "url": "https://www.kids-event.jp/event/20260422_mangalogue_hinotori/",
      "source": "kids",
      "cost": "paid",
      "ages": [
        "family"
      ],
      "cats": [
        "festival"
      ],
      "area": "other",
      "desc": "2026年3月28日（土）に誕生した「モン タカナワ：ザ ミュージアム オブ ナラティブズ」では、こけら落とし公演「MANGALOGUE（マンガローグ）：火の鳥」を2026年4月22日（水）～5月16日（土）に開催！",
      "id": 61
    },
    {
      "title": "ぐるぐる展—進化しつづける人類の物語",
      "date": "2026-03-28",
      "endDate": "2026-03-28",
      "place": "東京都",
      "url": "https://www.kids-event.jp/event/20260328_tgc_spiral/",
      "source": "kids",
      "cost": "paid",
      "ages": [
        "family"
      ],
      "cats": [
        "festival"
      ],
      "area": "other",
      "desc": "2026年3月28日（土）に誕生した「モン タカナワ：ザ ミュージアム オブ ナラティブズ」では、開館を記念した特別展「ぐるぐる展—進化しつづける人類の物語」を2026年3月28日（土）～9月23日（水・祝）に開催！",
      "id": 62
    },
    {
      "title": "高輪ワールドフェスティバル2026（TAKANAWA WORLD FESTIVAL 2026）",
      "date": "2026-03-28",
      "endDate": "2026-05-05",
      "place": "東京都",
      "url": "https://www.kids-event.jp/event/20260505_tgc_worldfes/",
      "source": "kids",
      "cost": "paid",
      "ages": [
        "family"
      ],
      "cats": [
        "festival"
      ],
      "area": "other",
      "desc": "2026年3月28日（土）にグランドオープンを迎えた「高輪ゲートウェイシティ」ではゴールデンウィークに多彩なイベントを開催！「高輪ワールドフェスティバル2026」は2026年5月5日（火・祝）～6日（水・休）に開催！",
      "id": 63
    },
    {
      "title": "高輪ゲートウェイシティ キッチンカーフェス",
      "date": "2026-03-28",
      "endDate": "2026-05-02",
      "place": "東京都",
      "url": "https://www.kids-event.jp/event/20260502_tgc_kitchencarfes/",
      "source": "kids",
      "cost": "paid",
      "ages": [
        "family"
      ],
      "cats": [
        "festival"
      ],
      "area": "other",
      "desc": "2026年3月28日（土）にグランドオープンを迎えた「高輪ゲートウェイシティ」ではゴールデンウィークに多彩なイベントを開催！「高輪ゲートウェイシティ キッチンカーフェス」は2026年5月2日（土）～3日（日）に開催！",
      "id": 64
    },
    {
      "title": "お台場ファンライジング～楽しくアガる！真夏のエンタメ最前線～",
      "date": "2026-07-25",
      "endDate": "2026-07-25",
      "place": "東京都",
      "url": "https://www.kids-event.jp/event/20260725_odaiba_fanrising/",
      "source": "kids",
      "cost": "paid",
      "ages": [
        "family"
      ],
      "cats": [
        "festival"
      ],
      "area": "other",
      "desc": "多彩な番組、キャラクターが集結し、ここでしか味わえない楽しさを届けるリアルイベント「お台場ファンライジング」が2026年7月25日（土）〜8月23日（日）にフジテレビ本社屋で開催！",
      "id": 65
    },
    {
      "title": "めざましWANGANフェス～人気バラエティと夏の最強コラボ～",
      "date": "2026-08-03",
      "endDate": "2026-08-03",
      "place": "東京都",
      "url": "https://www.kids-event.jp/event/20260803_mezamashi_wanganfes/",
      "source": "kids",
      "cost": "paid",
      "ages": [
        "family"
      ],
      "cats": [
        "festival"
      ],
      "area": "other",
      "desc": "話題のアーティスト、アイドル、芸人、俳優、インフルエンサーが大集合するイベント「めざましWANGANフェス～人気バラエティと夏の最強コラボ～」が、2026年8月3日（月）～9日（日）と8月13日（木）・14日（金）の9日間にわたり豊洲PIT",
      "id": 66
    },
    {
      "title": "TORANOMON HILLS PLAY PARK vol.3（虎ノ門ヒルズ プレイパーク vol.3）＆「SWEETS & FLOWER」（スイーツ＆フラワー）",
      "date": "2026-04-23",
      "endDate": "2026-04-23",
      "place": "東京都",
      "url": "https://www.kids-event.jp/event/20260503toranomonhillsplaypark/",
      "source": "kids",
      "cost": "paid",
      "ages": [
        "family"
      ],
      "cats": [
        "festival"
      ],
      "area": "other",
      "desc": "ゴールデンウィークに虎ノ門ヒルズでワークショップや春のスイーツを楽しめる「TORANOMON HILLS PLAY PARK vol.3」（虎ノ門ヒルズ プレイパーク vol.3）＆「SWEETS & FLOWER」（スイーツ＆フラワー）が",
      "id": 67
    },
    {
      "title": "2026年 親子で楽しむゴールデンウィーク “おすすめ映画”！",
      "date": "2026-04-23",
      "endDate": "2026-04-23",
      "place": "東京都",
      "url": "https://www.kids-event.jp/special/2026gw_movie/",
      "source": "kids",
      "cost": "paid",
      "ages": [
        "family"
      ],
      "cats": [
        "festival"
      ],
      "area": "other",
      "desc": "子どもと一緒に楽しめる2026年ゴールデンウィークおすすめ映画！いよいよ待望の『ザ・スーパーマリオギャラクシー・ムービー』や『映画 ラブライブ！』、そして仮面ライダー生誕55周年記念作『アギトー超能力戦争ー』が公開！ 大人気公開中の『映画ド",
      "id": 68
    },
    {
      "title": "【取材レポート】キティとアンパンマンの意外な絆？「サンリオ展 FINAL」で語られた、世界を救う「カワイイ」の哲学",
      "date": "2026-04-09",
      "endDate": "2026-04-09",
      "place": "東京都",
      "url": "https://www.kids-event.jp/report/20260409_sanrio_exhibition/",
      "source": "kids",
      "cost": "paid",
      "ages": [
        "family"
      ],
      "cats": [
        "festival"
      ],
      "area": "other",
      "desc": "「サンリオ展 FINAL ver. ニッポンのカワイイ文化60年史」が2026年4月9日（木）～6月21日（日）に森アーツセンターギャラリーで開催！ サンリオの60年を超える歴史を辿るとともに、「カワイイ」文化の根底にあるサンリオの想いを貴",
      "id": 69
    },
    {
      "title": "【取材レポート】M!LK 曽野舜太さん＆吉田仁人さんがサンリオキャラと「爆裂愛してる」を夢のダンスコラボ！ 推しとの対面に「かわいすぎて滅！」連発！「2026年サンリオキャラクター大賞」開幕イベント",
      "date": "2026-04-09",
      "endDate": "2026-04-09",
      "place": "東京都",
      "url": "https://www.kids-event.jp/report/20260409_sanrio_character_ranking/",
      "source": "kids",
      "cost": "paid",
      "ages": [
        "family"
      ],
      "cats": [
        "festival"
      ],
      "area": "other",
      "desc": "「2026年サンリオキャラクター大賞」開幕イベントが4月9日（木）東京・恵比寿で開催！ スペシャルゲストとして「M!LK」からクロミ “推し” の曽野舜太さんとシナモロール “推し” の吉田仁人さんが登場し「爆裂愛してる」を夢のダンスコラボ",
      "id": 70
    },
    {
      "title": "手塚治虫特集！",
      "date": "2026-04-23",
      "endDate": "2026-04-23",
      "place": "東京都",
      "url": "https://www.kids-event.jp/special/20260408_tezukaosamu_special/",
      "source": "kids",
      "cost": "paid",
      "ages": [
        "family"
      ],
      "cats": [
        "nature"
      ],
      "area": "other",
      "desc": "『火の鳥』『ブラック・ジャック』『どろろ』『鉄腕アトム』『三つ目がとおる』など、ぜひ子どもたちにも手塚治虫作品に触れてほしいと思い、今まで取材した手塚治虫先生に関するコンテンツをまとめてみました！",
      "id": 71
    },
    {
      "title": "スマートシティフェスタ2026",
      "date": "2026-04-24",
      "endDate": "2026-04-24",
      "place": "東京都",
      "url": "https://www.kids-event.jp/event/20260424_smartcityfes/",
      "source": "kids",
      "cost": "free",
      "ages": [
        "family"
      ],
      "cats": [
        "festival"
      ],
      "area": "other",
      "desc": "AR・VRをはじめとする最新のデジタル技術を活用した先端サービスを体験できるイベント「スマートシティフェスタ2026」が、2026年4月24日（金）〜26日（日）に東京・西新宿エリアで開催！参加無料！",
      "id": 72
    },
    {
      "title": "【取材レポート】新内眞衣さんが実演！『マンガローグ：火の鳥』の新感覚没入型マンガ体験！ AIユーミン発表、制作秘話を語るトークショーも！",
      "date": "2026-04-22",
      "endDate": "2026-04-22",
      "place": "東京都",
      "url": "https://www.kids-event.jp/report/20260406_mangalogue_hinotori/",
      "source": "kids",
      "cost": "paid",
      "ages": [
        "family"
      ],
      "cats": [
        "workshop"
      ],
      "area": "other",
      "desc": "「モン タカナワ」こけら落とし公演となる新感覚没入型マンガ体験『マンガローグ：火の鳥』を元乃木坂46 新内眞衣さんが実演！2026年4月22日（水）から上演！AIユーミン発表、制作秘話を語るトークショーも！",
      "id": 73
    },
    {
      "title": "『キッズイベント』ライター・編集者 募集！",
      "date": "2026-04-23",
      "endDate": "2026-04-23",
      "place": "東京都",
      "url": "https://www.kids-event.jp/special/2026_spring_staff_recruitment/",
      "source": "kids",
      "cost": "paid",
      "ages": [
        "family"
      ],
      "cats": [
        "festival"
      ],
      "area": "other",
      "desc": "『キッズイベント』のライター・編集者を募集。『キッズイベント』の記事制作にご協力いただけるライター、編集者を募集しています。ご興味のある方は、ぜひお力添えください。",
      "id": 74
    },
    {
      "title": "映画名探偵プリキュア！",
      "date": "2026-09-18",
      "endDate": "2026-09-18",
      "place": "東京都",
      "url": "https://www.kids-event.jp/movie/20260918_precure/",
      "source": "kids",
      "cost": "paid",
      "ages": [
        "family"
      ],
      "cats": [
        "festival"
      ],
      "area": "other",
      "desc": "プリキュアシリーズ最新作「名探偵プリキュア！」が映画化！「映画名探偵プリキュア！」が2026年9月18日（金）全国ロードショー！",
      "id": 75
    },
    {
      "title": "【仮面ライダー55周年発表会レポ】夏映画ゼッツの奇跡の共闘から、次作『仮面ライダーマイス』初解禁＆アギト・カブト復活、3つの新映画レーベル始動！",
      "date": "2026-04-03",
      "endDate": "2026-04-03",
      "place": "東京都",
      "url": "https://www.kids-event.jp/report/20260403_kamenrider55/",
      "source": "kids",
      "cost": "paid",
      "ages": [
        "family"
      ],
      "cats": [
        "festival"
      ],
      "area": "other",
      "desc": "2026年4月3日（金）で生誕55周年を迎える「仮面ライダーシリーズ」、今後に向けた展開についての「仮面ライダー生誕55周年発表会」が開催！仮面ライダーゼッツの夏映画やアギト・カブトの映画、そして次作『仮面ライダーマイス』も発表！",
      "id": 76
    },
    {
      "title": "仮面ライダーゼッツ＆超宇宙刑事ギャバン インフィニティ　Wヒーロー夏映画2026",
      "date": "2026-07-24",
      "endDate": "2026-07-24",
      "place": "東京都",
      "url": "https://www.kids-event.jp/movie/20260724_zeztz_gavan/",
      "source": "kids",
      "cost": "paid",
      "ages": [
        "family"
      ],
      "cats": [
        "festival"
      ],
      "area": "other",
      "desc": "『仮面ライダーゼッツ＆超宇宙刑事ギャバン インフィニティ　Wヒーロー夏映画2026』が、2026年7月24日（金）豪華2本立てで全国公開！",
      "id": 77
    },
    {
      "title": "パウ・パトロール ザ・ダイノ・ムービー",
      "date": "2026-07-24",
      "endDate": "2026-07-24",
      "place": "東京都",
      "url": "https://www.kids-event.jp/movie/20260724_pawpatrol/",
      "source": "kids",
      "cost": "paid",
      "ages": [
        "family"
      ],
      "cats": [
        "festival"
      ],
      "area": "other",
      "desc": "“パウパト” の愛称で大人気のアニメシリーズ「パウ・パトロール」の劇場版第3弾となる最新作『パウ・パトロール ザ・ダイノ・ムービー』が、2026年7月24日（金）に全国公開！",
      "id": 78
    },
    {
      "title": "映画 ラブライブ！蓮ノ空女学院スクールアイドルクラブ Bloom Garden Party",
      "date": "2026-05-08",
      "endDate": "2026-05-08",
      "place": "東京都",
      "url": "https://www.kids-event.jp/movie/20260508_lovelive/",
      "source": "kids",
      "cost": "paid",
      "ages": [
        "family"
      ],
      "cats": [
        "festival"
      ],
      "area": "other",
      "desc": "ラブライブ！シリーズより「蓮ノ空」が待望の完全新作映画化！『映画 ラブライブ！蓮ノ空女学院スクールアイドルクラブ Bloom Garden Party』が、2026年5月8日（金）に全国公開！",
      "id": 79
    },
    {
      "title": "SBI舞花火 in 千葉・稲毛海浜公園（いなげの浜）feat. SKY ORCHESTRA",
      "date": "2026-05-30",
      "endDate": "2026-05-30",
      "place": "東京都",
      "url": "https://www.kids-event.jp/event/20260530_sbimaihanabi/",
      "source": "kids",
      "cost": "paid",
      "ages": [
        "family"
      ],
      "cats": [
        "nature"
      ],
      "area": "other",
      "desc": "花火と音楽を楽しむ「SBI舞花火 in 千葉・稲毛海浜公園（いなげの浜）feat. SKY ORCHESTRA」が、2026年5月30日（土）いなげ海浜公園で開催！",
      "id": 80
    },
    {
      "title": "東京たま大恐竜博",
      "date": "2026-04-29",
      "endDate": "2026-04-29",
      "place": "東京都",
      "url": "https://www.kids-event.jp/event/20260429_tama_kyouryu/",
      "source": "kids",
      "cost": "paid",
      "ages": [
        "family"
      ],
      "cats": [
        "festival"
      ],
      "area": "other",
      "desc": "大迫力で動き迫る実物大恐竜など、恐竜が生きている世界への没入感を体験することができる「東京たま大恐竜博」が、2026年4月29日（水・祝）〜5月6日（水・祝）東京たま未来メッセで開催！",
      "id": 81
    },
    {
      "title": "謎解き冒険ラリー不思議ハンターin大師公園",
      "date": "2026-04-18",
      "endDate": "2026-04-18",
      "place": "東京都",
      "url": "https://www.kids-event.jp/event/20260418_npotashizan/",
      "source": "kids",
      "cost": "paid",
      "ages": [
        "family"
      ],
      "cats": [
        "nature"
      ],
      "area": "other",
      "desc": "謎解きイベント2026年4月18日（土）〜5月6日（水・祝）に開催！",
      "id": 82
    },
    {
      "title": "東京の子ども無料遊び場15選【2026年版】｜完全無料から子ども無料まで年齢別に完全ガイド",
      "date": "2026-04-23",
      "endDate": "2026-04-23",
      "place": "東京都",
      "url": "https://www.kids-event.jp/tips/free-kids-tokyo/",
      "source": "kids",
      "cost": "free",
      "ages": [
        "family"
      ],
      "cats": [
        "festival"
      ],
      "area": "other",
      "desc": "土日に子どもを連れてどこかに行くと、入場料だけで家族全員分が数千円かかることがあります。テーマパークや大型水族館は、気軽に何度も行ける値段ではありません。 でも東京には、無料で子どもを遊ばせられる場所が意外なほど多くあり […]",
      "id": 83
    },
    {
      "title": "東京の雨の日｜子連れ室内おでかけ15選【2026年版】年齢別・無料スポット完全ガイド",
      "date": "2026-04-23",
      "endDate": "2026-04-23",
      "place": "東京都",
      "url": "https://www.kids-event.jp/tips/rainy-day-kids-tokyo/",
      "source": "kids",
      "cost": "free",
      "ages": [
        "family"
      ],
      "cats": [
        "festival"
      ],
      "area": "other",
      "desc": "「また雨か……今週末、子どもをどこに連れていけばいいんだろう」 そんなため息をついたことが、一度はあるのではないでしょうか。天気予報を見るたびに頭を抱えて、でも家にこもれば子どもはエネルギーを持て余します。この記事では、 […]",
      "id": 84
    },
    {
      "title": "東京のGW子連れおでかけ15選【2026年版】｜5/4・5/5無料施設＆穴場スポット年齢別ガイド",
      "date": "2026-04-23",
      "endDate": "2026-04-23",
      "place": "東京都",
      "url": "https://www.kids-event.jp/tips/gw-kids-tokyo/",
      "source": "kids",
      "cost": "free",
      "ages": [
        "family"
      ],
      "cats": [
        "festival"
      ],
      "area": "other",
      "desc": "ゴールデンウィークが来るたびに「どこへ行くか」を調べる時間がかかります。どこに行っても混んでいます。予約は取れません。料金も高いです。子どもを連れてGWに動くことが、なぜかいつも疲れで終わってしまいます。 そんな繰り返し […]",
      "id": 85
    },
    {
      "title": "東京の1歳向け室内遊び場15選【2026年版】｜専用スペースあり・ハイハイ対応スポット完全ガイド",
      "date": "2026-04-23",
      "endDate": "2026-04-23",
      "place": "東京都",
      "url": "https://www.kids-event.jp/tips/indoor-play-1year-tokyo/",
      "source": "kids",
      "cost": "paid",
      "ages": [
        "baby",
        "toddler"
      ],
      "cats": [
        "festival"
      ],
      "area": "other",
      "desc": "雨の日に家にこもっていると、1歳の子どもがぐずり始めます。公園に連れていけない日が続くと、親のほうも煮詰まります。でも「1歳でも大丈夫な施設ってどこ？」と調べると、対象年齢が3歳以上だったり、ベビーカーが入れなかったりす […]",
      "id": 86
    },
    {
      "title": "【高輪ゲートウェイシティ全面開業】親子で “ぐるぐる” を楽しむ「モン タカナワ」は電車見学・100畳の畳・足湯まで揃った新感覚ミュージアム！食のエンタメ「ミムレ」も！",
      "date": "2026-03-28",
      "endDate": "2026-03-28",
      "place": "東京都",
      "url": "https://www.kids-event.jp/report/20260325_tgc/",
      "source": "kids",
      "cost": "paid",
      "ages": [
        "family"
      ],
      "cats": [
        "museum"
      ],
      "area": "other",
      "desc": "「高輪ゲートウェイシティ」に「ザ リンクピラーツー」と「モン タカナワ」が新たに誕生！ これにより高輪ゲートウェイシティは全面開業、2026年3月28日（土）にまちびらきが行われました！「モン タカナワ」と「ザ リンクピラーツー」内の食のエ",
      "id": 87
    },
    {
      "title": "チェンバー・フィルハーモニック東京 第39回演奏会",
      "date": "2026-04-23",
      "endDate": "2026-04-23",
      "place": "東京都内",
      "url": "https://www.concertsquare.jp/blog/2026/202603314886229.html",
      "source": "concert",
      "cost": "free",
      "ages": [
        "preschool",
        "elementary",
        "family"
      ],
      "cats": [
        "concert"
      ],
      "area": "other",
      "desc": "",
      "id": 88
    },
    {
      "title": "3人のバッハが紡いだ新しい風",
      "date": "2026-04-23",
      "endDate": "2026-04-23",
      "place": "東京都内",
      "url": "https://www.concertsquare.jp/blog/2026/202603091777424.html",
      "source": "concert",
      "cost": "free",
      "ages": [
        "preschool",
        "elementary",
        "family"
      ],
      "cats": [
        "concert"
      ],
      "area": "other",
      "desc": "",
      "id": 89
    },
    {
      "title": "オーケストラ・ラム・スール",
      "date": "2026-04-23",
      "endDate": "2026-04-23",
      "place": "東京都内",
      "url": "https://www.concertsquare.jp/blog/2026/2025071554725.html",
      "source": "concert",
      "cost": "free",
      "ages": [
        "preschool",
        "elementary",
        "family"
      ],
      "cats": [
        "concert"
      ],
      "area": "other",
      "desc": "",
      "id": 90
    },
    {
      "title": "NTT東日本東京吹奏楽団 第59回定期演奏会",
      "date": "2026-04-23",
      "endDate": "2026-04-23",
      "place": "東京都内",
      "url": "https://www.concertsquare.jp/blog/2026/202603177759545.html",
      "source": "concert",
      "cost": "free",
      "ages": [
        "preschool",
        "elementary",
        "family"
      ],
      "cats": [
        "concert"
      ],
      "area": "other",
      "desc": "",
      "id": 91
    },
    {
      "title": "陸上自衛隊東部方面音楽隊第85回定期演奏会",
      "date": "2026-04-23",
      "endDate": "2026-04-23",
      "place": "東京都内",
      "url": "https://www.concertsquare.jp/blog/2026/202604162389551.html",
      "source": "concert",
      "cost": "free",
      "ages": [
        "preschool",
        "elementary",
        "family"
      ],
      "cats": [
        "concert"
      ],
      "area": "other",
      "desc": "",
      "id": 92
    },
    {
      "title": "ASK歌劇団 第4回オペラ公演",
      "date": "2026-04-23",
      "endDate": "2026-04-23",
      "place": "東京都内",
      "url": "https://www.concertsquare.jp/blog/2026/202603101854690.html",
      "source": "concert",
      "cost": "free",
      "ages": [
        "preschool",
        "elementary",
        "family"
      ],
      "cats": [
        "concert"
      ],
      "area": "other",
      "desc": "",
      "id": 93
    },
    {
      "title": "第22回みなとみらいアイメイトチャリティーコンサート",
      "date": "2026-04-23",
      "endDate": "2026-04-23",
      "place": "東京都内",
      "url": "https://www.concertsquare.jp/blog/2026/202512059773983.html",
      "source": "concert",
      "cost": "free",
      "ages": [
        "preschool",
        "elementary",
        "family"
      ],
      "cats": [
        "concert"
      ],
      "area": "other",
      "desc": "",
      "id": 94
    },
    {
      "title": "ル スコアール管弦楽団 第59回演奏会",
      "date": "2026-04-23",
      "endDate": "2026-04-23",
      "place": "東京都内",
      "url": "https://www.concertsquare.jp/blog/2026/20260415548022.html",
      "source": "concert",
      "cost": "free",
      "ages": [
        "preschool",
        "elementary",
        "family"
      ],
      "cats": [
        "concert"
      ],
      "area": "other",
      "desc": "",
      "id": 95
    },
    {
      "title": "豊島区管弦楽団 第101回定期演奏会",
      "date": "2026-04-23",
      "endDate": "2026-04-23",
      "place": "東京都内",
      "url": "https://www.concertsquare.jp/blog/2026/202604042929618.html",
      "source": "concert",
      "cost": "free",
      "ages": [
        "preschool",
        "elementary",
        "family"
      ],
      "cats": [
        "concert"
      ],
      "area": "other",
      "desc": "",
      "id": 96
    },
    {
      "title": "FAF管弦楽団 第69回定期演奏会",
      "date": "2026-04-23",
      "endDate": "2026-04-23",
      "place": "東京都内",
      "url": "https://www.concertsquare.jp/blog/2026/202604109305031.html",
      "source": "concert",
      "cost": "free",
      "ages": [
        "preschool",
        "elementary",
        "family"
      ],
      "cats": [
        "concert"
      ],
      "area": "other",
      "desc": "",
      "id": 97
    },
    {
      "title": "パイプオルガン・プロムナードコンサート 99th",
      "date": "2026-04-23",
      "endDate": "2026-04-23",
      "place": "東京都内",
      "url": "https://www.concertsquare.jp/blog/2026/202602277086484.html",
      "source": "concert",
      "cost": "free",
      "ages": [
        "preschool",
        "elementary",
        "family"
      ],
      "cats": [
        "concert"
      ],
      "area": "other",
      "desc": "",
      "id": 98
    }
  ]
}